{
  "text": "Message 970 of 4024\nI don’t know what you mean? We should chat rather than misinterpret in email. Can we do that?\nSent:02/02/2024 at 05:17 PM\nFrom:Robert Moyer\nTo:Christine Moyer (First Viewed: 02/02/2024 at 05:28 PM)\nSubject:Re: Gorgeous Day: Dad & AD\nMessage 971 of 4024\nAre we going to try to work together on our list? I thought we were last night and obviously it was a 14 hour break. Just want to know if that was a\none way blast and I’ll hear from you tomorrow, or we plan to try to resolve some things. Just let me know. Thanks!\nSent:02/02/2024 at 05:20 PM\nFrom:Robert Moyer\nTo:Christine Moyer (First Viewed: 02/02/2024 at 05:27 PM)\nSubject:OFW\nMessage 972 of 4024\nOk. I’ll work on ice\nSent:02/02/2024 at 05:27 PM\nFrom:Christine Moyer\nTo:Robert Moyer (First Viewed: 02/02/2024 at 05:28 PM)\nSubject:Re: Ad basketball\nMessage 973 of 4024\nWhat time can you do post basketball? I can see Deavon availability otherwise I’d have you organize a lugg\nI’ll need your list\nSent:02/02/2024 at 05:28 PM\nFrom:Christine Moyer\nTo:Robert Moyer (First Viewed: 02/02/2024 at 05:28 PM)\nSubject:Re: Packages / Items\nMessage 974 of 4024\nNo. I’m really not comfortable doing that.\nDr Brown sent us times . I emailed you it works for elsa and Adrian and for\nYou to confirm.\nSent:02/02/2024 at 05:29 PM\nFrom:Christine Moyer\nTo:Robert Moyer (First Viewed: 02/02/2024 at 05:29 PM)\nSubject:Re: Gorgeous Day: Dad & AD",
  "metadata": {
    "section": "Page 247 of 1048",
    "type": "section",
    "position": 60,
    "continues": true,
    "part": 61,
    "total_parts": 239,
    "estimated_tokens": 350
  }
}