{
  "text": "I’ll have to think through what other regular services are done.\nSent:02/06/2024 at 03:57 PM\nFrom:Christine Moyer\nTo:Robert Moyer (First Viewed: 02/06/2024 at 04:02 PM)\nSubject:Re: Home Services <<Not Urgent>>\nMessage 1155 of 4024\nYou, sweet lady, are AWESOME!!! But as mentioned I did not need it right away. So thank you! \nSent:02/06/2024 at 04:08 PM\nFrom:Robert Moyer\nTo:Christine Moyer (First Viewed: 02/06/2024 at 04:28 PM)\nSubject:Re: Home Services <<Not Urgent>>",
  "metadata": {
    "section": "- 59?",
    "type": "section",
    "position": 110,
    "continues": true,
    "part": 111,
    "total_parts": 239,
    "estimated_tokens": 118
  }
}